setup.cfg
setup.py
pygame_anisprite/__init__.py
pygame_anisprite/anisprite.py
pygame_anisprite.egg-info/PKG-INFO
pygame_anisprite.egg-info/SOURCES.txt
pygame_anisprite.egg-info/dependency_links.txt
pygame_anisprite.egg-info/requires.txt
pygame_anisprite.egg-info/top_level.txt