Metadata-Version: 1.1
Name: pygame-anisprite
Version: 1.0.0
Summary: Animated sprites for PyGame!
Home-page: UNKNOWN
Author: Lily Mayfield
Author-email: lily.m.mayfield@gmail.com
License: MIT
Keywords: games gaming sprites 2d pygame animation
Platform: UNKNOWN
Classifier: Development Status :: 3 - Alpha
Classifier: Intended Audience :: Developers
Classifier: Natural Language :: English
Classifier: License :: OSI Approved :: MIT License
Classifier: Programming Language :: Python :: 2.7
Classifier: Programming Language :: Python :: 3.4
Classifier: Topic :: Software Development :: Libraries :: pygame
